studentvue/__init__.py
studentvue/helpers.py
studentvue/models.py
studentvue/scraper.py
studentvue/studentvue.py
studentvue_old-1.0.dist-info/LICENSE
studentvue_old-1.0.dist-info/METADATA
studentvue_old-1.0.dist-info/WHEEL
studentvue_old-1.0.dist-info/top_level.txt
studentvue_old-1.0.dist-info/RECORD
