Metadata-Version: 2.1
Name: studentvue-old
Version: 1.0
Summary: Python Scraper for StudentVue Portals
Home-page: https://github.com/kajchang/studentvuescraper
Author: Kai Chang
License: MIT
Platform: UNKNOWN
Requires-Dist: robobrowser
